Metadata-Version: 2.1
Name: SylvacV2
Version: 0.0.3
Summary: Phần mềm kết nối với thiết bị đo DiaTest
Home-page: https://github.com/huynhquoc1990/Sylvac_V02.git
Author: Huynh
Author-email: huynhquoc1990@gmail.com
License: MIT
Platform: UNKNOWN
Classifier: Programming Language :: Python :: 3
Classifier: License :: OSI Approved :: MIT License
Classifier: Operating System :: OS Independent
License-File: LICENSE
